uupt_mcp_server/__init__.py
uupt_mcp_server/__main__.py
uupt_mcp_server/order.py
uupt_mcp_server-0.2.7.dist-info/METADATA
uupt_mcp_server-0.2.7.dist-info/WHEEL
uupt_mcp_server-0.2.7.dist-info/entry_points.txt
uupt_mcp_server-0.2.7.dist-info/licenses/LICENSE
uupt_mcp_server-0.2.7.dist-info/RECORD
