Metadata-Version: 2.4
Name: uupt-mcp-server
Version: 0.2.7
Summary: uupt.com openapi mcp server
Author: uupt
License-File: LICENSE
Requires-Python: >=3.10
Requires-Dist: bs4>=0.0.2
Requires-Dist: dashscope>=1.23.5
Requires-Dist: dotenv>=0.9.9
Requires-Dist: httpx>=0.28.1
Requires-Dist: mcp[cli]>=1.9.4
